aws_kinesis_agg/__init__.py
aws_kinesis_agg/aggregator.py
aws_kinesis_agg/config_pb2.py
aws_kinesis_agg/deaggregator.py
aws_kinesis_agg/messages_pb2.py
aws_kinesis_agg-1.2.3.dist-info/LICENSE.txt
aws_kinesis_agg-1.2.3.dist-info/METADATA
aws_kinesis_agg-1.2.3.dist-info/WHEEL
aws_kinesis_agg-1.2.3.dist-info/top_level.txt
aws_kinesis_agg-1.2.3.dist-info/RECORD
