Metadata-Version: 2.1
Name: aws_kinesis_agg
Version: 1.2.3
Summary: Python module to assist in taking advantage of the Kinesis message aggregation format for both aggregation and deaggregation.
Home-page: http://github.com/awslabs/kinesis-aggregation
Author: Ian Meyers
Author-email: meyersi@amazon.com
License: Apache-2.0
Keywords: aws,kinesis,aggregation,deaggregation,kpl
Classifier: Development Status :: 5 - Production/Stable
Classifier: Intended Audience :: Developers
Classifier: License :: OSI Approved :: Apache Software License
Classifier: Natural Language :: English
Classifier: Operating System :: OS Independent
Classifier: Programming Language :: Python
Classifier: Programming Language :: Python :: 2.7
Classifier: Programming Language :: Python :: 3.6
Classifier: Topic :: Software Development :: Libraries :: Python Modules
Classifier: Topic :: Utilities
License-File: LICENSE.txt
